package ak.CookLoco.SkyWars.database;

public class SQLQueryThread
  extends Thread
{
  /* Error */
  public void run()
  {
    // Byte code:
    //   0: ldc2_w 17
    //   3: invokestatic 22	java/lang/Thread:sleep	(J)V
    //   6: goto +4 -> 10
    //   9: astore_1
    //   10: getstatic 28	ak/CookLoco/SkyWars/SkyWars:sql_query	Ljava/util/concurrent/CopyOnWriteArrayList;
    //   13: invokevirtual 34	java/util/concurrent/CopyOnWriteArrayList:iterator	()Ljava/util/Iterator;
    //   16: astore_2
    //   17: goto +188 -> 205
    //   20: aload_2
    //   21: invokeinterface 40 1 0
    //   26: checkcast 42	java/lang/String
    //   29: astore_1
    //   30: aconst_null
    //   31: astore_3
    //   32: aconst_null
    //   33: astore 4
    //   35: invokestatic 48	ak/CookLoco/SkyWars/database/SQLConnectionThread:getConnection	()Ljava/sql/Connection;
    //   38: aload_1
    //   39: invokeinterface 54 2 0
    //   44: astore 4
    //   46: aload 4
    //   48: invokeinterface 60 1 0
    //   53: pop
    //   54: goto +111 -> 165
    //   57: astore 5
    //   59: aload 5
    //   61: invokevirtual 63	java/lang/Exception:printStackTrace	()V
    //   64: new 65	java/lang/StringBuilder
    //   67: dup
    //   68: aload_1
    //   69: invokestatic 69	java/lang/String:valueOf	(Ljava/lang/Object;)Ljava/lang/String;
    //   72: invokespecial 72	java/lang/StringBuilder:<init>	(Ljava/lang/String;)V
    //   75: ldc 74
    //   77: invokevirtual 78	java/lang/StringBuilder:append	(Ljava/lang/String;)Ljava/lang/StringBuilder;
    //   80: aload_0
    //   81: invokevirtual 84	java/lang/Object:getClass	()Ljava/lang/Class;
    //   84: invokevirtual 87	java/lang/StringBuilder:append	(Ljava/lang/Object;)Ljava/lang/StringBuilder;
    //   87: invokevirtual 91	java/lang/StringBuilder:toString	()Ljava/lang/String;
    //   90: invokestatic 94	ak/CookLoco/SkyWars/SkyWars:log	(Ljava/lang/String;)V
    //   93: aload 4
    //   95: ifnull +10 -> 105
    //   98: aload 4
    //   100: invokeinterface 97 1 0
    //   105: aload_3
    //   106: ifnull +91 -> 197
    //   109: aload_3
    //   110: invokeinterface 98 1 0
    //   115: goto +82 -> 197
    //   118: astore 7
    //   120: aload 7
    //   122: invokevirtual 99	java/sql/SQLException:printStackTrace	()V
    //   125: goto +72 -> 197
    //   128: astore 6
    //   130: aload 4
    //   132: ifnull +10 -> 142
    //   135: aload 4
    //   137: invokeinterface 97 1 0
    //   142: aload_3
    //   143: ifnull +19 -> 162
    //   146: aload_3
    //   147: invokeinterface 98 1 0
    //   152: goto +10 -> 162
    //   155: astore 7
    //   157: aload 7
    //   159: invokevirtual 99	java/sql/SQLException:printStackTrace	()V
    //   162: aload 6
    //   164: athrow
    //   165: aload 4
    //   167: ifnull +10 -> 177
    //   170: aload 4
    //   172: invokeinterface 97 1 0
    //   177: aload_3
    //   178: ifnull +19 -> 197
    //   181: aload_3
    //   182: invokeinterface 98 1 0
    //   187: goto +10 -> 197
    //   190: astore 7
    //   192: aload 7
    //   194: invokevirtual 99	java/sql/SQLException:printStackTrace	()V
    //   197: getstatic 28	ak/CookLoco/SkyWars/SkyWars:sql_query	Ljava/util/concurrent/CopyOnWriteArrayList;
    //   200: aload_1
    //   201: invokevirtual 105	java/util/concurrent/CopyOnWriteArrayList:remove	(Ljava/lang/Object;)Z
    //   204: pop
    //   205: aload_2
    //   206: invokeinterface 109 1 0
    //   211: ifne -191 -> 20
    //   214: goto -214 -> 0
    // Line number table:
    //   Java source line #19	-> byte code offset #0
    //   Java source line #20	-> byte code offset #10
    //   Java source line #21	-> byte code offset #30
    //   Java source line #22	-> byte code offset #32
    //   Java source line #25	-> byte code offset #35
    //   Java source line #26	-> byte code offset #46
    //   Java source line #27	-> byte code offset #54
    //   Java source line #28	-> byte code offset #59
    //   Java source line #29	-> byte code offset #64
    //   Java source line #33	-> byte code offset #93
    //   Java source line #34	-> byte code offset #98
    //   Java source line #36	-> byte code offset #105
    //   Java source line #37	-> byte code offset #109
    //   Java source line #40	-> byte code offset #115
    //   Java source line #41	-> byte code offset #120
    //   Java source line #31	-> byte code offset #128
    //   Java source line #33	-> byte code offset #130
    //   Java source line #34	-> byte code offset #135
    //   Java source line #36	-> byte code offset #142
    //   Java source line #37	-> byte code offset #146
    //   Java source line #40	-> byte code offset #152
    //   Java source line #41	-> byte code offset #157
    //   Java source line #43	-> byte code offset #162
    //   Java source line #33	-> byte code offset #165
    //   Java source line #34	-> byte code offset #170
    //   Java source line #36	-> byte code offset #177
    //   Java source line #37	-> byte code offset #181
    //   Java source line #40	-> byte code offset #187
    //   Java source line #41	-> byte code offset #192
    //   Java source line #45	-> byte code offset #197
    //   Java source line #20	-> byte code offset #205
    //   Java source line #18	-> byte code offset #214
    // Local variable table:
    //   start	length	slot	name	signature
    //   0	217	0	this	SQLQueryThread
    //   9	1	1	localInterruptedException	InterruptedException
    //   29	172	1	str	String
    //   16	190	2	localIterator	java.util.Iterator
    //   31	151	3	localObject1	Object
    //   33	138	4	localPreparedStatement	java.sql.PreparedStatement
    //   57	3	5	localException	Exception
    //   128	35	6	localObject2	Object
    //   118	3	7	localSQLException1	java.sql.SQLException
    //   155	3	7	localSQLException2	java.sql.SQLException
    //   190	3	7	localSQLException3	java.sql.SQLException
    // Exception table:
    //   from	to	target	type
    //   0	6	9	java/lang/InterruptedException
    //   35	54	57	java/lang/Exception
    //   93	115	118	java/sql/SQLException
    //   35	93	128	finally
    //   130	152	155	java/sql/SQLException
    //   165	187	190	java/sql/SQLException
  }
}


/* Location:              C:\Users\Cody\AppData\Roaming\Skype\My Skype Received Files\SkyWars.jar!\ak\CookLoco\SkyWars\database\SQLQueryThread.class
 * Java compiler version: 7 (51.0)
 * JD-Core Version:       0.7.1
 */